QConnectWinapp/GUIAction.resource
QConnectWinapp/QConnectWinapp.pdf
QConnectWinapp/__init__.py
QConnectWinapp/version.py
QConnectWinapp/ActionHandlers/__init__.py
QConnectWinapp/ActionHandlers/element_handler.py
QConnectWinapp/WinappDriver/__init__.py
QConnectWinapp/WinappDriver/winapp_client.py
QConnectWinapp/tools/bin/release/AutomationInspector.exe
QConnectWinapp/tools/bin/release/cpprest_2_10.dll
QConnectWinapp/tools/bin/release/jsoncpp.dll
QConnectWinapp/tools/bin/release/Plugins/WinappDriverPlugin.dll
robotframework_qconnect_winapp-1.0.3.dist-info/LICENSE
robotframework_qconnect_winapp-1.0.3.dist-info/LICENSE.txt
robotframework_qconnect_winapp-1.0.3.dist-info/METADATA
robotframework_qconnect_winapp-1.0.3.dist-info/WHEEL
robotframework_qconnect_winapp-1.0.3.dist-info/top_level.txt
robotframework_qconnect_winapp-1.0.3.dist-info/RECORD
