Metadata-Version: 2.1
Name: robotframework-qconnect-winapp
Version: 1.0.3
Summary: Robot Framework QConnect library extension for Winapp GUI testing
Home-page: https://github.com/test-fullautomation/robotframework-qconnect-winapp
Author: Nguyen Huynh Tri Cuong
Author-email: cuong.nguyenhuynhtri@vn.bosch.com
License: UNKNOWN
Platform: UNKNOWN
Classifier: Programming Language :: Python :: 3
Classifier: License :: OSI Approved :: Apache Software License
Classifier: Operating System :: Microsoft :: Windows
Classifier: Development Status :: 4 - Beta
Classifier: Intended Audience :: Developers
Classifier: Topic :: Software Development
Requires-Python: >=3.0
License-File: LICENSE
License-File: LICENSE.txt
Requires-Dist: robotframework
Requires-Dist: QConnectBase
Requires-Dist: Appium-Python-Client
Requires-Dist: selenium
